[

    {
        "type_slug": "product-types",
        "name": "Simple"
    },
    {
        "type_slug": "product-types",
        "name": "Configurable"
    },
    {
        "type_slug": "product-types",
        "name": "Digital"
    },
    {
        "type_slug": "product-types",
        "name": "Ticket"
    },
    {
        "type_slug": "product-types",
        "name": "Quotation"
    },
    {
        "type_slug": "product-types",
        "name": "Voucher"
    },
    {
        "type_slug": "store-status",
        "name": "Pending"
    },
    {
        "type_slug": "store-status",
        "name": "Approved"
    },
    {
        "type_slug": "store-status",
        "name": "Rejected"
    },
    {
        "type_slug": "vendor-status",
        "name": "Pending"
    },
    {
        "type_slug": "vendor-status",
        "name": "Approved"
    },
    {
        "type_slug": "vendor-status",
        "name": "Rejected"
    },
    {
        "type_slug": "brand-status",
        "name": "Pending"
    },
    {
        "type_slug": "brand-status",
        "name": "Approved"
    },
    {
        "type_slug": "brand-status",
        "name": "Rejected"
    },
    {
        "type_slug": "product-status",
        "name": "Pending"
    },
    {
        "type_slug": "product-status",
        "name": "Approved"
    },
    {
        "type_slug": "product-status",
        "name": "Rejected"
    },
    {
        "type_slug": "product-vendor-status",
        "name": "Pending"
    },
    {
        "type_slug": "product-vendor-status",
        "name": "Approved"
    },
    {
        "type_slug": "product-vendor-status",
        "name": "Rejected"
    },
    {
        "type_slug": "product-variation-status",
        "name": "Pending"
    },
    {
        "type_slug": "product-variation-status",
        "name": "Approved"
    },
    {
        "type_slug": "product-variation-status",
        "name": "Rejected"
    },
    {
        "type_slug": "product-medias-status",
        "name": "Pending"
    },
    {
        "type_slug": "product-medias-status",
        "name": "Approved"
    },
    {
        "type_slug": "product-medias-status",
        "name": "Rejected"
    }
]
